{
  "hash": "ccacbbb0eb5c1e46825d51476022ae33",
  "result": {
    "markdown": "---\ntitle: \"Challenge 7: Visualizing Multiple Dimensions\"\nauthor: \"Surya Praneeth Reddy Chirasani\"\ndescription: \"\"\ndate: \"01/27/2023\"\nformat:\n  html:\n    toc: true\n    code-fold: true\n    code-copy: true\n    code-tools: true\ncategories:\n  - challenge_7\n  - eggs\n---\n\n::: {.cell}\n\n```{.r .cell-code}\nlibrary(tidyverse)\nlibrary(\"readxl\")\nlibrary(ggplot2)\nlibrary(lubridate)\nknitr::opts_chunk$set(echo = TRUE)\n```\n:::\n\n\n## Data Description\n\nFor this challenge, I have decided to work with eggs dataset. This dataset has monthly price amount of different sizes(large and extra large) of half dozen and dozen eggs. \n\n\n::: {.cell}\n\n```{.r .cell-code}\neggs_data <-read_csv(\"_data/eggs_tidy.csv\")\n```\n\n::: {.cell-output .cell-output-stderr}\n```\nRows: 120 Columns: 6\n── Column specification ────────────────────────────────────────────────────────\nDelimiter: \",\"\nchr (1): month\ndbl (5): year, large_half_dozen, large_dozen, extra_large_half_dozen, extra_...\n\nℹ Use `spec()` to retrieve the full column specification for this data.\nℹ Specify the column types or set `show_col_types = FALSE` to quiet this message.\n```\n:::\n\n```{.r .cell-code}\neggs_data\n```\n\n::: {.cell-output .cell-output-stdout}\n```\n# A tibble: 120 × 6\n   month      year large_half_dozen large_dozen extra_large_half_dozen extra_l…¹\n   <chr>     <dbl>            <dbl>       <dbl>                  <dbl>     <dbl>\n 1 January    2004             126         230                    132       230 \n 2 February   2004             128.        226.                   134.      230 \n 3 March      2004             131         225                    137       230 \n 4 April      2004             131         225                    137       234.\n 5 May        2004             131         225                    137       236 \n 6 June       2004             134.        231.                   137       241 \n 7 July       2004             134.        234.                   137       241 \n 8 August     2004             134.        234.                   137       241 \n 9 September  2004             130.        234.                   136.      241 \n10 October    2004             128.        234.                   136.      241 \n# … with 110 more rows, and abbreviated variable name ¹​extra_large_dozen\n```\n:::\n:::\n\n## Tidying Data\n\nIn order to plot a graph of varying prices for different sizes and amount of eggs, I need to pivot the data longer and separate the data based on size and amount. This is done as follows\n\n\n::: {.cell}\n\n```{.r .cell-code}\neggs_tidy <- eggs_data %>%\n  pivot_longer(cols=3:6, names_to=\"type\", values_to = \"price\") %>%\n  mutate(type=str_replace(type,\"extra_large\",\"extra large\"),\n         type=str_replace(type,\"half_dozen\",\"half dozen\")) %>%\n  separate(type,into=c(\"size\",\"amount\"),sep=\"_\") %>%\n  mutate(date = str_c(year, month, sep=\" \")) %>%\n  mutate(date = ym(date))\neggs_tidy\n```\n\n::: {.cell-output .cell-output-stdout}\n```\n# A tibble: 480 × 6\n   month     year size        amount     price date      \n   <chr>    <dbl> <chr>       <chr>      <dbl> <date>    \n 1 January   2004 large       half dozen  126  2004-01-01\n 2 January   2004 large       dozen       230  2004-01-01\n 3 January   2004 extra large half dozen  132  2004-01-01\n 4 January   2004 extra large dozen       230  2004-01-01\n 5 February  2004 large       half dozen  128. 2004-02-01\n 6 February  2004 large       dozen       226. 2004-02-01\n 7 February  2004 extra large half dozen  134. 2004-02-01\n 8 February  2004 extra large dozen       230  2004-02-01\n 9 March     2004 large       half dozen  131  2004-03-01\n10 March     2004 large       dozen       225  2004-03-01\n# … with 470 more rows\n```\n:::\n:::\n\n::: {.cell}\n\n```{.r .cell-code}\nggplot(eggs_tidy,aes(date,price)) +\n  geom_line(color = \"steelblue\", size = 1)+\n  scale_x_date()+\n  scale_y_continuous(labels=scales::dollar_format(), limits=c(0,300)) +\n  facet_grid(size ~ amount) +\n  labs(x=\"Date\",y=\"Average Price Per Carton\")+\n  theme(axis.text.x=element_text(angle=90))\n```\n\n::: {.cell-output .cell-output-stderr}\n```\nWarning: Using `size` aesthetic for lines was deprecated in ggplot2 3.4.0.\nℹ Please use `linewidth` instead.\n```\n:::\n\n::: {.cell-output-display}\n![](SuryaPraneethReddyChirasani_challenge7_files/figure-html/unnamed-chunk-4-1.png){width=672}\n:::\n:::\n\n\nSince we are just trying to visualize variation of price with time for different sizes and amount, I decided to plot a simple line graph in a 4x4 grid, plotting all the four different kinds\n",
    "supporting": [
      "SuryaPraneethReddyChirasani_challenge7_files"
    ],
    "filters": [
      "rmarkdown/pagebreak.lua"
    ],
    "includes": {},
    "engineDependencies": {},
    "preserve": {},
    "postProcess": true
  }
}